MANIFEST.in
README.rst
setup.cfg
setup.py
bin/secretunicornspyspark-jars
deps/jars/activation-1.1.jar
deps/jars/apacheds-i18n-2.0.0-M15.jar
deps/jars/apacheds-kerberos-codec-2.0.0-M15.jar
deps/jars/api-asn1-api-1.0.0-M20.jar
deps/jars/api-util-1.0.0-M20.jar
deps/jars/asm-3.1.jar
deps/jars/avro-1.7.4.jar
deps/jars/aws-java-sdk-core-1.11.185.jar
deps/jars/aws-java-sdk-kms-1.11.185.jar
deps/jars/aws-java-sdk-s3-1.11.185.jar
deps/jars/aws-java-sdk-sts-1.11.185.jar
deps/jars/commons-beanutils-1.7.0.jar
deps/jars/commons-beanutils-core-1.8.0.jar
deps/jars/commons-cli-1.2.jar
deps/jars/commons-codec-1.4.jar
deps/jars/commons-collections-3.2.2.jar
deps/jars/commons-compress-1.4.1.jar
deps/jars/commons-configuration-1.6.jar
deps/jars/commons-digester-1.8.jar
deps/jars/commons-io-2.4.jar
deps/jars/commons-lang-2.6.jar
deps/jars/commons-logging-1.1.3.jar
deps/jars/commons-math3-3.1.1.jar
deps/jars/commons-net-3.1.jar
deps/jars/curator-client-2.7.1.jar
deps/jars/curator-framework-2.7.1.jar
deps/jars/curator-recipes-2.7.1.jar
deps/jars/gson-2.2.4.jar
deps/jars/guava-11.0.2.jar
deps/jars/hadoop-annotations-2.8.1.jar
deps/jars/hadoop-auth-2.8.1.jar
deps/jars/hadoop-aws-2.8.1.jar
deps/jars/hadoop-common-2.8.1.jar
deps/jars/htrace-core4-4.0.1-incubating.jar
deps/jars/httpclient-4.5.2.jar
deps/jars/httpcore-4.4.4.jar
deps/jars/ion-java-1.0.2.jar
deps/jars/jackson-annotations-2.6.0.jar
deps/jars/jackson-core-2.6.7.jar
deps/jars/jackson-core-asl-1.9.13.jar
deps/jars/jackson-databind-2.6.7.1.jar
deps/jars/jackson-dataformat-cbor-2.6.7.jar
deps/jars/jackson-jaxrs-1.8.3.jar
deps/jars/jackson-mapper-asl-1.9.13.jar
deps/jars/jackson-xc-1.8.3.jar
deps/jars/java-xmlbuilder-0.4.jar
deps/jars/jaxb-api-2.2.2.jar
deps/jars/jaxb-impl-2.2.3-1.jar
deps/jars/jcip-annotations-1.0.jar
deps/jars/jersey-core-1.9.jar
deps/jars/jersey-json-1.9.jar
deps/jars/jersey-server-1.9.jar
deps/jars/jets3t-0.9.0.jar
deps/jars/jettison-1.1.jar
deps/jars/jetty-6.1.26.jar
deps/jars/jetty-sslengine-6.1.26.jar
secretunicorns_pyspark.egg-info/PKG-INFO
secretunicorns_pyspark.egg-info/SOURCES.txt
secretunicorns_pyspark.egg-info/dependency_links.txt
secretunicorns_pyspark.egg-info/not-zip-safe
secretunicorns_pyspark.egg-info/requires.txt
secretunicorns_pyspark.egg-info/top_level.txt
