Metadata-Version: 1.1
Name: secretunicorns-pyspark
Version: 1.0
Summary: secretunicorns PySpark bindings
Home-page: https://secretunicorns.org
Author: Secret Unicorns Union
Author-email: UNKNOWN
License: Apache License 2.0
Download-URL: https://github.com/secretunicorns-spark.git
Platform: UNKNOWN
